{
  "paintings": [
    {
      "name": "arch_illager",
      "x": 16,
      "y": 32
    },
    {
      "name": "dog",
      "square": 32
    },
    {
      "name": "panda",
      "square": 32
    },
    {
      "name": "pig",
      "square": 16
    },
    {
      "name": "portal",
      "square": 32
    },
    {
      "name": "trail",
      "square": 32
    },
    {
      "name": "bee",
      "x": 32,
      "y": 16
    },
    {
      "name": "creeper_face",
      "square": 16
    },
    {
      "name": "duck",
      "square": 32
    },
    {
      "name": "feesh",
      "x": 16,
      "y": 32
    },
    {
      "name": "frog",
      "square": 32
    },
    {
      "name": "parrot",
      "square": 16
    },
    {
      "name": "puffer",
      "square": 16
    },
    {
      "name": "sunflower",
      "x": 16,
      "y": 32
    }
  ]
}