{
  "type": "bonsaitrees2:sapling/endergetic/poise",
  "version": 3,
  "ref": {
    "a": {"block":"endergetic:poise_stem_glowing","properties":{"axis":"y"}},
    "b": {"block":"minecraft:bubble_coral_block"},
    "c": {"block":"endergetic:poise_stem","properties":{"axis":"y"}}
  },
  "shape": [
    [
      "         ",
      "         ",
      "   bbb   ",
      "  bbbbb  ",
      "  bbbbb  ",
      "  bbbbb  ",
      "   ccb   ",
      "         ",
      "         ",
      "         ",
      "         ",
      "         ",
      "         ",
      "         ",
      "         ",
      "         ",
      "         ",
      "         ",
      "         ",
      "         ",
      "         ",
      "         "
    ],
    [
      "         ",
      "   bbb   ",
      " bb   bb ",
      " b     b ",
      " c     a ",
      " c     a ",
      " bc   bb ",
      "   ccc   ",
      "         ",
      "         ",
      "         ",
      "         ",
      "         ",
      "         ",
      "         ",
      "         ",
      "         ",
      "         ",
      "         ",
      "         ",
      "         ",
      "         "
    ],
    [
      "   bbb   ",
      "  b   b  ",
      " b     b ",
      "b       b",
      "b       b",
      "b       b",
      " b     c ",
      "  ccccc  ",
      "   ccc   ",
      "         ",
      "         ",
      "         ",
      "         ",
      "         ",
      "         ",
      "         ",
      "         ",
      "         ",
      "         ",
      "         ",
      "         ",
      "         "
    ],
    [
      "  bbbbb  ",
      " b     b ",
      "b       b",
      "b       b",
      "b       b",
      "b       b",
      "b       b",
      " cccccca ",
      "  ccccc  ",
      "    c    ",
      "         ",
      "         ",
      "         ",
      "         ",
      "         ",
      "         ",
      "    c    ",
      "    c    ",
      "    c    ",
      "    c    ",
      "   ccc   ",
      "   ccc   "
    ],
    [
      "  bbbbb  ",
      " b     b ",
      "b       b",
      "b       b",
      "a       b",
      "c       c",
      "c       c",
      " ccccccc ",
      "  cccac  ",
      "   ccc   ",
      "    a    ",
      "    a    ",
      "    a    ",
      "    a    ",
      "    c    ",
      "    c    ",
      "   ccc   ",
      "   ccc   ",
      "   ccc   ",
      "   ccc   ",
      "   ccc   ",
      "   ccc   "
    ],
    [
      "  bbbbb  ",
      " b     b ",
      "b       b",
      "b       b",
      "b       b",
      "b       b",
      "b       b",
      " acccccc ",
      "  ccccc  ",
      "    c    ",
      "         ",
      "         ",
      "         ",
      "    b    ",
      "         ",
      "         ",
      "    c    ",
      "    a    ",
      "    c    ",
      "    c    ",
      "   cca   ",
      "   ccc   "
    ],
    [
      "   bbb   ",
      "  b   b  ",
      " b     b ",
      "b       b",
      "b       b",
      "b       b",
      " b     b ",
      "  cccca  ",
      "   ccc   ",
      "         ",
      "         ",
      "         ",
      "         ",
      "         ",
      "         ",
      "         ",
      "         ",
      "         ",
      "         ",
      "         ",
      "         ",
      "         "
    ],
    [
      "         ",
      "   bbb   ",
      " bb   bb ",
      " b     b ",
      " b     b ",
      " b     b ",
      " bb   bb ",
      "   ccc   ",
      "         ",
      "         ",
      "         ",
      "         ",
      "         ",
      "         ",
      "         ",
      "         ",
      "         ",
      "         ",
      "         ",
      "         ",
      "         ",
      "         "
    ],
    [
      "         ",
      "         ",
      "   bbb   ",
      "  bbbbb  ",
      "  bbabb  ",
      "  bbcbb  ",
      "   bcb   ",
      "         ",
      "         ",
      "         ",
      "         ",
      "         ",
      "         ",
      "         ",
      "         ",
      "         ",
      "         ",
      "         ",
      "         ",
      "         ",
      "         ",
      "         "
    ]
  ]
}
